LICENSE
MANIFEST.in
README.md
setup.cfg
setup.py
neovim/__init__.py
neovim/compat.py
neovim/util.py
neovim.egg-info/PKG-INFO
neovim.egg-info/SOURCES.txt
neovim.egg-info/dependency_links.txt
neovim.egg-info/not-zip-safe
neovim.egg-info/requires.txt
neovim.egg-info/top_level.txt
neovim/api/__init__.py
neovim/api/buffer.py
neovim/api/common.py
neovim/api/nvim.py
neovim/api/tabpage.py
neovim/api/window.py
neovim/msgpack_rpc/__init__.py
neovim/msgpack_rpc/async_session.py
neovim/msgpack_rpc/msgpack_stream.py
neovim/msgpack_rpc/session.py
neovim/msgpack_rpc/event_loop/__init__.py
neovim/msgpack_rpc/event_loop/asyncio.py
neovim/msgpack_rpc/event_loop/base.py
neovim/msgpack_rpc/event_loop/uv.py
neovim/plugin/__init__.py
neovim/plugin/decorators.py
neovim/plugin/host.py
neovim/plugin/script_host.py
test/test_buffer.py
test/test_client_rpc.py
test/test_concurrency.py
test/test_decorators.py
test/test_events.py
test/test_host.py
test/test_tabpage.py
test/test_vim.py
test/test_window.py