Metadata-Version: 2.1
Name: neovim
Version: 0.3.0
Summary: Python client to neovim
Home-page: http://github.com/neovim/python-client
Author: Thiago de Arruda
Author-email: tpadilha84@gmail.com
License: Apache
Download-URL: https://github.com/neovim/python-client/archive/0.3.0.tar.gz
Platform: UNKNOWN
Provides-Extra: pyuv
Provides-Extra: test
